better_logging/__init__.py
better_logging/core.py
better_logging/main.py
better_logging/static/css/app.fe185133.css
better_logging/static/css/chunk-vendors.b765c399.css
better_logging/static/favicon.ico
better_logging/static/fonts/MaterialIcons-Regular.0509ab09.woff2
better_logging/static/fonts/MaterialIcons-Regular.29b882f0.woff
better_logging/static/fonts/MaterialIcons-Regular.96c47680.eot
better_logging/static/fonts/MaterialIcons-Regular.da4ea5cd.ttf
better_logging/static/index.html
better_logging/static/js/app.c6abeb52.js
better_logging/static/js/app.c6abeb52.js.map
better_logging/static/js/chunk-2d0de531.baaedc5a.js
better_logging/static/js/chunk-2d0de531.baaedc5a.js.map
better_logging/static/js/chunk-vendors.6668a4e4.js
better_logging/static/js/chunk-vendors.6668a4e4.js.map
better_logging/static/version.txt
better_logging/static/vuetify-logo-dark.png
better_logging-0.1.4.dist-info/entry_points.txt
better_logging-0.1.4.dist-info/WHEEL
better_logging-0.1.4.dist-info/METADATA
better_logging-0.1.4.dist-info/RECORD
