Metadata-Version: 2.1
Name: better-logging
Version: 0.1.4
Summary: Simple UI for Logback Postgres DBAppender
Home-page: https://github.com/b7w/better-logging
License: MIT
Author: B7W
Author-email: b7w@isudo.ru
Requires-Python: >=3.6,<4.0
Classifier: License :: OSI Approved :: MIT License
Classifier: Programming Language :: Python :: 3
Classifier: Programming Language :: Python :: 3.6
Classifier: Programming Language :: Python :: 3.7
Classifier: Programming Language :: Python :: 3.8
Requires-Dist: aiohttp (>=3.6.2,<4.0.0)
Requires-Dist: arrow (>=0.15.5,<0.16.0)
Requires-Dist: asyncpg (>=0.20.1,<0.21.0)
Project-URL: Repository, https://github.com/b7w/better-logging
